smcdk/__init__.py
smcdk/__version__.py
smcdk/api/__init__.py
smcdk/api/mediasoup_client.py
smcdk/api/mediasoup_listener.py
smcdk/api/mediasoup_signaler.py
smcdk/api/multimedia_runtime.py
smcdk/api/notification_listener.py
smcdk/api/request_listener.py
smcdk/api/room_peer.py
smcdk/api/stats_collector.py
smcdk/consumer.py
smcdk/data_consumer.py
smcdk/data_producer.py
smcdk/deps/h264_profile_level_id/__init__.py
smcdk/deps/h264_profile_level_id/__version__.py
smcdk/deps/h264_profile_level_id/core.py
smcdk/deps/h264_profile_level_id/index.py
smcdk/deps/h264_profile_level_id/LICENSE-MIT_origin_author
smcdk/deps/README.md
smcdk/deps/sdp_transform/__init__.py
smcdk/deps/sdp_transform/__version__.py
smcdk/deps/sdp_transform/grammar.py
smcdk/deps/sdp_transform/index.py
smcdk/deps/sdp_transform/LICENSE-MIT_origin_author
smcdk/deps/sdp_transform/parser.py
smcdk/deps/sdp_transform/writer.py
smcdk/device.py
smcdk/emitter.py
smcdk/errors.py
smcdk/handlers/__init__.py
smcdk/handlers/aiortc_handler.py
smcdk/handlers/handler_interface.py
smcdk/handlers/sdp/__init__.py
smcdk/handlers/sdp/common_utils.py
smcdk/handlers/sdp/media_section.py
smcdk/handlers/sdp/remote_sdp.py
smcdk/handlers/sdp/unified_plan_utils.py
smcdk/log/__init__.py
smcdk/log/logger.py
smcdk/models/__init__.py
smcdk/models/handler_interface.py
smcdk/models/transport.py
smcdk/ortc.py
smcdk/producer.py
smcdk/rtp_parameters.py
smcdk/scalability_modes.py
smcdk/sctp_parameters.py
smcdk/transport.py
smcdk-1.0.1.dist-info/WHEEL
smcdk-1.0.1.dist-info/METADATA
smcdk-1.0.1.dist-info/RECORD
