Metadata-Version: 2.1
Name: smcdk
Version: 1.0.1
Summary: mediasoup-client-pysdk, a simple mediasoup client development kit, i.e. 'smcdk', fork from pymediasoup and do more
Home-page: https://github.com/jimdragongod/mediasoup-client-pysdk
License: MIT
Author: Jim DG
Author-email: jimdragongod@126.com
Requires-Python: >=3.8.0,<4.0.0
Classifier: License :: OSI Approved :: MIT License
Classifier: Programming Language :: Python :: 3
Classifier: Programming Language :: Python :: 3.8
Classifier: Programming Language :: Python :: 3.9
Classifier: Programming Language :: Python :: 3.10
Classifier: Programming Language :: Python :: 3.11
Requires-Dist: aiortc (>=1.2.0,<2.0.0)
Requires-Dist: pydantic (>=1.8.1,<2.0.0)
Requires-Dist: pyee (>=8.1.0,<9.0.0)
Project-URL: Repository, https://github.com/jimdragongod/mediasoup-client-pysdk
